<pkg-contents spec="1.12"><f n="iStat pro.wdgt" o="slice" g="staff" p="16832" pt="/Users/slice/Projects/hwsensors3/package/Application/iStat pro.wdgt" m="false" t="file"><f n=".identity" o="slice" g="staff" p="33216"/><f n=".svn" o="slice" g="staff" p="16877"><f n="entries" o="slice" g="staff" p="33060"/><f n="prop-base" o="slice" g="staff" p="16877"><f n=".identity.svn-base" o="slice" g="staff" p="33060"/><f n="AnimationObject.js.svn-base" o="slice" g="staff" p="33060"/><f n="Animator.js.svn-base" o="slice" g="staff" p="33060"/><f n="core.css.svn-base" o="slice" g="staff" p="33060"/><f n="Default.png.svn-base" o="slice" g="staff" p="33060"/><f n="DiskObject.js.svn-base" o="slice" g="staff" p="33060"/><f n="Icon.png.svn-base" o="slice" g="staff" p="33060"/><f n="Info.plist.svn-base" o="slice" g="staff" p="33060"/><f n="iStatpro.html.svn-base" o="slice" g="staff" p="33060"/><f n="NetworkObject.js.svn-base" o="slice" g="staff" p="33060"/><f n="Tall.js.svn-base" o="slice" g="staff" p="33060"/><f n="Wide.js.svn-base" o="slice" g="staff" p="33060"/><f n="Workers.js.svn-base" o="slice" g="staff" p="33060"/></f><f n="props" o="slice" g="staff" p="16877"/><f n="text-base" o="slice" g="staff" p="16877"><f n=".identity.svn-base" o="slice" g="staff" p="33060"/><f n="AnimationObject.js.svn-base" o="slice" g="staff" p="33060"/><f n="Animator.js.svn-base" o="slice" g="staff" p="33060"/><f n="core.css.svn-base" o="slice" g="staff" p="33060"/><f n="Default.png.svn-base" o="slice" g="staff" p="33060"/><f n="DiskObject.js.svn-base" o="slice" g="staff" p="33060"/><f n="Icon.png.svn-base" o="slice" g="staff" p="33060"/><f n="Info.plist.svn-base" o="slice" g="staff" p="33060"/><f n="iStatpro.html.svn-base" o="slice" g="staff" p="33060"/><f n="NetworkObject.js.svn-base" o="slice" g="staff" p="33060"/><f n="Tall.js.svn-base" o="slice" g="staff" p="33060"/><f n="Wide.js.svn-base" o="slice" g="staff" p="33060"/><f n="Workers.js.svn-base" o="slice" g="staff" p="33060"/></f><f n="tmp" o="slice" g="staff" p="16877"><f n="prop-base" o="slice" g="staff" p="16877"/><f n="props" o="slice" g="staff" p="16877"/><f n="text-base" o="slice" g="staff" p="16877"/></f></f><f n="AnimationObject.js" o="slice" g="staff" p="33216"/><f n="Animator.js" o="slice" g="staff" p="33216"/><f n="AppleClasses" o="slice" g="staff" p="16832"><f n=".svn" o="slice" g="staff" p="16877"><f n="entries" o="slice" g="staff" p="33060"/><f n="prop-base" o="slice" g="staff" p="16877"><f n="AppleScrollArea.js.svn-base" o="slice" g="staff" p="33060"/><f n="AppleScrollbar.js.svn-base" o="slice" g="staff" p="33060"/></f><f n="props" o="slice" g="staff" p="16877"/><f n="text-base" o="slice" g="staff" p="16877"><f n="AppleScrollArea.js.svn-base" o="slice" g="staff" p="33060"/><f n="AppleScrollbar.js.svn-base" o="slice" g="staff" p="33060"/></f><f n="tmp" o="slice" g="staff" p="16877"><f n="prop-base" o="slice" g="staff" p="16877"/><f n="props" o="slice" g="staff" p="16877"/><f n="text-base" o="slice" g="staff" p="16877"/></f></f><f n="AppleScrollArea.js" o="slice" g="staff" p="33216"/><f n="AppleScrollbar.js" o="slice" g="staff" p="33216"/><f n="Images" o="slice" g="staff" p="16832"><f n=".svn" o="slice" g="staff" p="16877"><f n="entries" o="slice" g="staff" p="33060"/><f n="prop-base" o="slice" g="staff" p="16877"/><f n="props" o="slice" g="staff" p="16877"/><f n="text-base" o="slice" g="staff" p="16877"/><f n="tmp" o="slice" g="staff" p="16877"><f n="prop-base" o="slice" g="staff" p="16877"/><f n="props" o="slice" g="staff" p="16877"/><f n="text-base" o="slice" g="staff" p="16877"/></f></f></f></f><f n="core.css" o="slice" g="staff" p="33216"/><f n="css" o="slice" g="staff" p="16832"><f n=".svn" o="slice" g="staff" p="16877"><f n="entries" o="slice" g="staff" p="33060"/><f n="prop-base" o="slice" g="staff" p="16877"><f n="tall.css.svn-base" o="slice" g="staff" p="33060"/><f n="wide.css.svn-base" o="slice" g="staff" p="33060"/></f><f n="props" o="slice" g="staff" p="16877"/><f n="text-base" o="slice" g="staff" p="16877"><f n="tall.css.svn-base" o="slice" g="staff" p="33060"/><f n="wide.css.svn-base" o="slice" g="staff" p="33060"/></f><f n="tmp" o="slice" g="staff" p="16877"><f n="prop-base" o="slice" g="staff" p="16877"/><f n="props" o="slice" g="staff" p="16877"/><f n="text-base" o="slice" g="staff" p="16877"/></f></f><f n="tall" o="slice" g="staff" p="16832"><f n=".svn" o="slice" g="staff" p="16877"><f n="entries" o="slice" g="staff" p="33060"/><f n="prop-base" o="slice" g="staff" p="16877"><f n="blue.css.svn-base" o="slice" g="staff" p="33060"/><f n="fire.css.svn-base" o="slice" g="staff" p="33060"/><f n="graphite.css.svn-base" o="slice" g="staff" p="33060"/><f n="green.css.svn-base" o="slice" g="staff" p="33060"/><f n="grey.css.svn-base" o="slice" g="staff" p="33060"/><f n="pink.css.svn-base" o="slice" g="staff" p="33060"/><f n="purple.css.svn-base" o="slice" g="staff" p="33060"/><f n="putty.css.svn-base" o="slice" g="staff" p="33060"/><f n="red.css.svn-base" o="slice" g="staff" p="33060"/></f><f n="props" o="slice" g="staff" p="16877"/><f n="text-base" o="slice" g="staff" p="16877"><f n="blue.css.svn-base" o="slice" g="staff" p="33060"/><f n="fire.css.svn-base" o="slice" g="staff" p="33060"/><f n="graphite.css.svn-base" o="slice" g="staff" p="33060"/><f n="green.css.svn-base" o="slice" g="staff" p="33060"/><f n="grey.css.svn-base" o="slice" g="staff" p="33060"/><f n="pink.css.svn-base" o="slice" g="staff" p="33060"/><f n="purple.css.svn-base" o="slice" g="staff" p="33060"/><f n="putty.css.svn-base" o="slice" g="staff" p="33060"/><f n="red.css.svn-base" o="slice" g="staff" p="33060"/></f><f n="tmp" o="slice" g="staff" p="16877"><f n="prop-base" o="slice" g="staff" p="16877"/><f n="props" o="slice" g="staff" p="16877"/><f n="text-base" o="slice" g="staff" p="16877"/></f></f><f n="blue.css" o="slice" g="staff" p="33216"/><f n="fire.css" o="slice" g="staff" p="33216"/><f n="graphite.css" o="slice" g="staff" p="33216"/><f n="green.css" o="slice" g="staff" p="33216"/><f n="grey.css" o="slice" g="staff" p="33216"/><f n="pink.css" o="slice" g="staff" p="33216"/><f n="purple.css" o="slice" g="staff" p="33216"/><f n="putty.css" o="slice" g="staff" p="33216"/><f n="red.css" o="slice" g="staff" p="33216"/></f><f n="tall.css" o="slice" g="staff" p="33216"/><f n="wide" o="slice" g="staff" p="16832"><f n=".svn" o="slice" g="staff" p="16877"><f n="entries" o="slice" g="staff" p="33060"/><f n="prop-base" o="slice" g="staff" p="16877"><f n="blue.css.svn-base" o="slice" g="staff" p="33060"/><f n="fire.css.svn-base" o="slice" g="staff" p="33060"/><f n="graphite.css.svn-base" o="slice" g="staff" p="33060"/><f n="green.css.svn-base" o="slice" g="staff" p="33060"/><f n="grey.css.svn-base" o="slice" g="staff" p="33060"/><f n="pink.css.svn-base" o="slice" g="staff" p="33060"/><f n="purple.css.svn-base" o="slice" g="staff" p="33060"/><f n="putty.css.svn-base" o="slice" g="staff" p="33060"/><f n="red.css.svn-base" o="slice" g="staff" p="33060"/></f><f n="props" o="slice" g="staff" p="16877"/><f n="text-base" o="slice" g="staff" p="16877"><f n="blue.css.svn-base" o="slice" g="staff" p="33060"/><f n="fire.css.svn-base" o="slice" g="staff" p="33060"/><f n="graphite.css.svn-base" o="slice" g="staff" p="33060"/><f n="green.css.svn-base" o="slice" g="staff" p="33060"/><f n="grey.css.svn-base" o="slice" g="staff" p="33060"/><f n="pink.css.svn-base" o="slice" g="staff" p="33060"/><f n="purple.css.svn-base" o="slice" g="staff" p="33060"/><f n="putty.css.svn-base" o="slice" g="staff" p="33060"/><f n="red.css.svn-base" o="slice" g="staff" p="33060"/></f><f n="tmp" o="slice" g="staff" p="16877"><f n="prop-base" o="slice" g="staff" p="16877"/><f n="props" o="slice" g="staff" p="16877"/><f n="text-base" o="slice" g="staff" p="16877"/></f></f><f n="blue.css" o="slice" g="staff" p="33216"/><f n="fire.css" o="slice" g="staff" p="33216"/><f n="graphite.css" o="slice" g="staff" p="33216"/><f n="green.css" o="slice" g="staff" p="33216"/><f n="grey.css" o="slice" g="staff" p="33216"/><f n="pink.css" o="slice" g="staff" p="33216"/><f n="purple.css" o="slice" g="staff" p="33216"/><f n="putty.css" o="slice" g="staff" p="33216"/><f n="red.css" o="slice" g="staff" p="33216"/></f><f n="wide.css" o="slice" g="staff" p="33216"/></f><f n="Default.png" o="slice" g="staff" p="33216"/><f n="DiskObject.js" o="slice" g="staff" p="33216"/><f n="Icon.png" o="slice" g="staff" p="33216"/><f n="images" o="slice" g="staff" p="16832"><f n=".svn" o="slice" g="staff" p="16877"><f n="entries" o="slice" g="staff" p="33060"/><f n="prop-base" o="slice" g="staff" p="16877"><f n="battery_btkeyboard.png.svn-base" o="slice" g="staff" p="33060"/><f n="battery_btmouse.png.svn-base" o="slice" g="staff" p="33060"/><f n="battery_charging.png.svn-base" o="slice" g="staff" p="33060"/><f n="battery_mains.png.svn-base" o="slice" g="staff" p="33060"/><f n="battery_nomains.png.svn-base" o="slice" g="staff" p="33060"/><f n="button_netconnect.png.svn-base" o="slice" g="staff" p="33060"/><f n="button_netconnect_down.png.svn-base" o="slice" g="staff" p="33060"/><f n="button_netconnected.png.svn-base" o="slice" g="staff" p="33060"/><f n="button_netconnected_down.png.svn-base" o="slice" g="staff" p="33060"/><f n="button_netdisconnect.png.svn-base" o="slice" g="staff" p="33060"/><f n="button_netdisconnect_down.png.svn-base" o="slice" g="staff" p="33060"/><f n="button_netdisconnected.png.svn-base" o="slice" g="staff" p="33060"/><f n="button_netdisconnected_down.png.svn-base" o="slice" g="staff" p="33060"/><f n="button_networkeject.png.svn-base" o="slice" g="staff" p="33060"/><f n="button_networkeject_down.png.svn-base" o="slice" g="staff" p="33060"/><f n="defaultHD.png.svn-base" o="slice" g="staff" p="33060"/><f n="defaultProcessIcon.tiff.svn-base" o="slice" g="staff" p="33060"/><f n="IP_copied.png.svn-base" o="slice" g="staff" p="33060"/><f n="net_icon_airport.png.svn-base" o="slice" g="staff" p="33060"/><f n="net_icon_airport0.png.svn-base" o="slice" g="staff" p="33060"/><f n="net_icon_airport1.png.svn-base" o="slice" g="staff" p="33060"/><f n="net_icon_airport2.png.svn-base" o="slice" g="staff" p="33060"/><f n="net_icon_airport3.png.svn-base" o="slice" g="staff" p="33060"/><f n="net_icon_airport4.png.svn-base" o="slice" g="staff" p="33060"/><f n="net_icon_bluetooth.png.svn-base" o="slice" g="staff" p="33060"/><f n="net_icon_ethernet.png.svn-base" o="slice" g="staff" p="33060"/><f n="net_icon_firewire.png.svn-base" o="slice" g="staff" p="33060"/><f n="net_icon_modem.png.svn-base" o="slice" g="staff" p="33060"/><f n="net_icon_vpn.pdf.svn-base" o="slice" g="staff" p="33060"/></f><f n="props" o="slice" g="staff" p="16877"/><f n="text-base" o="slice" g="staff" p="16877"><f n="battery_btkeyboard.png.svn-base" o="slice" g="staff" p="33060"/><f n="battery_btmouse.png.svn-base" o="slice" g="staff" p="33060"/><f n="battery_charging.png.svn-base" o="slice" g="staff" p="33060"/><f n="battery_mains.png.svn-base" o="slice" g="staff" p="33060"/><f n="battery_nomains.png.svn-base" o="slice" g="staff" p="33060"/><f n="button_netconnect.png.svn-base" o="slice" g="staff" p="33060"/><f n="button_netconnect_down.png.svn-base" o="slice" g="staff" p="33060"/><f n="button_netconnected.png.svn-base" o="slice" g="staff" p="33060"/><f n="button_netconnected_down.png.svn-base" o="slice" g="staff" p="33060"/><f n="button_netdisconnect.png.svn-base" o="slice" g="staff" p="33060"/><f n="button_netdisconnect_down.png.svn-base" o="slice" g="staff" p="33060"/><f n="button_netdisconnected.png.svn-base" o="slice" g="staff" p="33060"/><f n="button_netdisconnected_down.png.svn-base" o="slice" g="staff" p="33060"/><f n="button_networkeject.png.svn-base" o="slice" g="staff" p="33060"/><f n="button_networkeject_down.png.svn-base" o="slice" g="staff" p="33060"/><f n="defaultHD.png.svn-base" o="slice" g="staff" p="33060"/><f n="defaultProcessIcon.tiff.svn-base" o="slice" g="staff" p="33060"/><f n="IP_copied.png.svn-base" o="slice" g="staff" p="33060"/><f n="net_icon_airport.png.svn-base" o="slice" g="staff" p="33060"/><f n="net_icon_airport0.png.svn-base" o="slice" g="staff" p="33060"/><f n="net_icon_airport1.png.svn-base" o="slice" g="staff" p="33060"/><f n="net_icon_airport2.png.svn-base" o="slice" g="staff" p="33060"/><f n="net_icon_airport3.png.svn-base" o="slice" g="staff" p="33060"/><f n="net_icon_airport4.png.svn-base" o="slice" g="staff" p="33060"/><f n="net_icon_bluetooth.png.svn-base" o="slice" g="staff" p="33060"/><f n="net_icon_ethernet.png.svn-base" o="slice" g="staff" p="33060"/><f n="net_icon_firewire.png.svn-base" o="slice" g="staff" p="33060"/><f n="net_icon_modem.png.svn-base" o="slice" g="staff" p="33060"/><f n="net_icon_vpn.pdf.svn-base" o="slice" g="staff" p="33060"/></f><f n="tmp" o="slice" g="staff" p="16877"><f n="prop-base" o="slice" g="staff" p="16877"/><f n="props" o="slice" g="staff" p="16877"/><f n="text-base" o="slice" g="staff" p="16877"/></f></f><f n="back" o="slice" g="staff" p="16832"><f n=".svn" o="slice" g="staff" p="16877"><f n="entries" o="slice" g="staff" p="33060"/><f n="prop-base" o="slice" g="staff" p="16877"><f n="back_bottom.png.svn-base" o="slice" g="staff" p="33060"/><f n="back_display.png.svn-base" o="slice" g="staff" p="33060"/><f n="back_general.png.svn-base" o="slice" g="staff" p="33060"/><f n="back_sections.png.svn-base" o="slice" g="staff" p="33060"/><f n="back_top.png.svn-base" o="slice" g="staff" p="33060"/><f n="button_donate.png.svn-base" o="slice" g="staff" p="33060"/><f n="button_donate_rollie.png.svn-base" o="slice" g="staff" p="33060"/><f n="button_done.png.svn-base" o="slice" g="staff" p="33060"/><f n="button_done_rollie.png.svn-base" o="slice" g="staff" p="33060"/><f n="button_install.png.svn-base" o="slice" g="staff" p="33060"/><f n="button_install_done.png.svn-base" o="slice" g="staff" p="33060"/><f n="button_install_ppc.png.svn-base" o="slice" g="staff" p="33060"/><f n="button_install_rollie.png.svn-base" o="slice" g="staff" p="33060"/><f n="button_iphone.png.svn-base" o="slice" g="staff" p="33060"/><f n="button_iphone_rollie.png.svn-base" o="slice" g="staff" p="33060"/><f n="button_paypal.png.svn-base" o="slice" g="staff" p="33060"/><f n="button_paypal_on.png.svn-base" o="slice" g="staff" p="33060"/><f n="button_resetbandwidth.png.svn-base" o="slice" g="staff" p="33060"/><f n="button_resetbandwidth_rolie.png.svn-base" o="slice" g="staff" p="33060"/><f n="button_update.png.svn-base" o="slice" g="staff" p="33060"/><f n="button_update_rollie.png.svn-base" o="slice" g="staff" p="33060"/><f n="checkbox_off.png.svn-base" o="slice" g="staff" p="33060"/><f n="checkbox_on.png.svn-base" o="slice" g="staff" p="33060"/><f n="display_background.png.svn-base" o="slice" g="staff" p="33060"/><f n="display_highlight.png.svn-base" o="slice" g="staff" p="33060"/><f n="tabs_display.png.svn-base" o="slice" g="staff" p="33060"/><f n="tabs_display_on.png.svn-base" o="slice" g="staff" p="33060"/><f n="tabs_display_rollie.png.svn-base" o="slice" g="staff" p="33060"/><f n="tabs_general.png.svn-base" o="slice" g="staff" p="33060"/><f n="tabs_general_on.png.svn-base" o="slice" g="staff" p="33060"/><f n="tabs_general_rollie.png.svn-base" o="slice" g="staff" p="33060"/><f n="tabs_sections.png.svn-base" o="slice" g="staff" p="33060"/><f n="tabs_sections_on.png.svn-base" o="slice" g="staff" p="33060"/><f n="tabs_sections_rollie.png.svn-base" o="slice" g="staff" p="33060"/></f><f n="props" o="slice" g="staff" p="16877"/><f n="text-base" o="slice" g="staff" p="16877"><f n="back_bottom.png.svn-base" o="slice" g="staff" p="33060"/><f n="back_display.png.svn-base" o="slice" g="staff" p="33060"/><f n="back_general.png.svn-base" o="slice" g="staff" p="33060"/><f n="back_sections.png.svn-base" o="slice" g="staff" p="33060"/><f n="back_top.png.svn-base" o="slice" g="staff" p="33060"/><f n="button_donate.png.svn-base" o="slice" g="staff" p="33060"/><f n="button_donate_rollie.png.svn-base" o="slice" g="staff" p="33060"/><f n="button_done.png.svn-base" o="slice" g="staff" p="33060"/><f n="button_done_rollie.png.svn-base" o="slice" g="staff" p="33060"/><f n="button_install.png.svn-base" o="slice" g="staff" p="33060"/><f n="button_install_done.png.svn-base" o="slice" g="staff" p="33060"/><f n="button_install_ppc.png.svn-base" o="slice" g="staff" p="33060"/><f n="button_install_rollie.png.svn-base" o="slice" g="staff" p="33060"/><f n="button_iphone.png.svn-base" o="slice" g="staff" p="33060"/><f n="button_iphone_rollie.png.svn-base" o="slice" g="staff" p="33060"/><f n="button_paypal.png.svn-base" o="slice" g="staff" p="33060"/><f n="button_paypal_on.png.svn-base" o="slice" g="staff" p="33060"/><f n="button_resetbandwidth.png.svn-base" o="slice" g="staff" p="33060"/><f n="button_resetbandwidth_rolie.png.svn-base" o="slice" g="staff" p="33060"/><f n="button_update.png.svn-base" o="slice" g="staff" p="33060"/><f n="button_update_rollie.png.svn-base" o="slice" g="staff" p="33060"/><f n="checkbox_off.png.svn-base" o="slice" g="staff" p="33060"/><f n="checkbox_on.png.svn-base" o="slice" g="staff" p="33060"/><f n="display_background.png.svn-base" o="slice" g="staff" p="33060"/><f n="display_highlight.png.svn-base" o="slice" g="staff" p="33060"/><f n="tabs_display.png.svn-base" o="slice" g="staff" p="33060"/><f n="tabs_display_on.png.svn-base" o="slice" g="staff" p="33060"/><f n="tabs_display_rollie.png.svn-base" o="slice" g="staff" p="33060"/><f n="tabs_general.png.svn-base" o="slice" g="staff" p="33060"/><f n="tabs_general_on.png.svn-base" o="slice" g="staff" p="33060"/><f n="tabs_general_rollie.png.svn-base" o="slice" g="staff" p="33060"/><f n="tabs_sections.png.svn-base" o="slice" g="staff" p="33060"/><f n="tabs_sections_on.png.svn-base" o="slice" g="staff" p="33060"/><f n="tabs_sections_rollie.png.svn-base" o="slice" g="staff" p="33060"/></f><f n="tmp" o="slice" g="staff" p="16877"><f n="prop-base" o="slice" g="staff" p="16877"/><f n="props" o="slice" g="staff" p="16877"/><f n="text-base" o="slice" g="staff" p="16877"/></f></f><f n="back_bottom.png" o="slice" g="staff" p="33216"/><f n="back_display.png" o="slice" g="staff" p="33216"/><f n="back_general.png" o="slice" g="staff" p="33216"/><f n="back_sections.png" o="slice" g="staff" p="33216"/><f n="back_top.png" o="slice" g="staff" p="33216"/><f n="button_donate.png" o="slice" g="staff" p="33216"/><f n="button_donate_rollie.png" o="slice" g="staff" p="33216"/><f n="button_done.png" o="slice" g="staff" p="33216"/><f n="button_done_rollie.png" o="slice" g="staff" p="33216"/><f n="button_install.png" o="slice" g="staff" p="33216"/><f n="button_install_done.png" o="slice" g="staff" p="33216"/><f n="button_install_ppc.png" o="slice" g="staff" p="33216"/><f n="button_install_rollie.png" o="slice" g="staff" p="33216"/><f n="button_iphone.png" o="slice" g="staff" p="33216"/><f n="button_iphone_rollie.png" o="slice" g="staff" p="33216"/><f n="button_paypal.png" o="slice" g="staff" p="33216"/><f n="button_paypal_on.png" o="slice" g="staff" p="33216"/><f n="button_resetbandwidth.png" o="slice" g="staff" p="33216"/><f n="button_resetbandwidth_rolie.png" o="slice" g="staff" p="33216"/><f n="button_update.png" o="slice" g="staff" p="33216"/><f n="button_update_rollie.png" o="slice" g="staff" p="33216"/><f n="checkbox_off.png" o="slice" g="staff" p="33216"/><f n="checkbox_on.png" o="slice" g="staff" p="33216"/><f n="display_background.png" o="slice" g="staff" p="33216"/><f n="display_highlight.png" o="slice" g="staff" p="33216"/><f n="tabs_display.png" o="slice" g="staff" p="33216"/><f n="tabs_display_on.png" o="slice" g="staff" p="33216"/><f n="tabs_display_rollie.png" o="slice" g="staff" p="33216"/><f n="tabs_general.png" o="slice" g="staff" p="33216"/><f n="tabs_general_on.png" o="slice" g="staff" p="33216"/><f n="tabs_general_rollie.png" o="slice" g="staff" p="33216"/><f n="tabs_sections.png" o="slice" g="staff" p="33216"/><f n="tabs_sections_on.png" o="slice" g="staff" p="33216"/><f n="tabs_sections_rollie.png" o="slice" g="staff" p="33216"/></f><f n="battery_btkeyboard.png" o="slice" g="staff" p="33216"/><f n="battery_btmouse.png" o="slice" g="staff" p="33216"/><f n="battery_charging.png" o="slice" g="staff" p="33216"/><f n="battery_mains.png" o="slice" g="staff" p="33216"/><f n="battery_nomains.png" o="slice" g="staff" p="33216"/><f n="button_netconnect.png" o="slice" g="staff" p="33216"/><f n="button_netconnect_down.png" o="slice" g="staff" p="33216"/><f n="button_netconnected.png" o="slice" g="staff" p="33216"/><f n="button_netconnected_down.png" o="slice" g="staff" p="33216"/><f n="button_netdisconnect.png" o="slice" g="staff" p="33216"/><f n="button_netdisconnect_down.png" o="slice" g="staff" p="33216"/><f n="button_netdisconnected.png" o="slice" g="staff" p="33216"/><f n="button_netdisconnected_down.png" o="slice" g="staff" p="33216"/><f n="button_networkeject.png" o="slice" g="staff" p="33216"/><f n="button_networkeject_down.png" o="slice" g="staff" p="33216"/><f n="common" o="slice" g="staff" p="16832"><f n=".svn" o="slice" g="staff" p="16877"><f n="entries" o="slice" g="staff" p="33060"/><f n="prop-base" o="slice" g="staff" p="16877"><f n="bar_horizontal_bg.png.svn-base" o="slice" g="staff" p="33060"/><f n="bar_horizontal_fire100.png.svn-base" o="slice" g="staff" p="33060"/><f n="bar_horizontal_fire125.png.svn-base" o="slice" g="staff" p="33060"/><f n="bar_horizontal_fire80.png.svn-base" o="slice" g="staff" p="33060"/><f n="bar_horizontal_fire82.png.svn-base" o="slice" g="staff" p="33060"/><f n="bar_horizontal_graphite.png.svn-base" o="slice" g="staff" p="33060"/><f n="bar_horizontal_orange.png.svn-base" o="slice" g="staff" p="33060"/><f n="bar_horizontal_pink.png.svn-base" o="slice" g="staff" p="33060"/><f n="bar_horizontal_purple.png.svn-base" o="slice" g="staff" p="33060"/><f n="bar_horizontal_red.png.svn-base" o="slice" g="staff" p="33060"/><f n="bar_horizontal_white.png.svn-base" o="slice" g="staff" p="33060"/><f n="bar_vertical_bg.png.svn-base" o="slice" g="staff" p="33060"/><f n="bar_vertical_graphite.png.svn-base" o="slice" g="staff" p="33060"/><f n="bar_vertical_orange.png.svn-base" o="slice" g="staff" p="33060"/><f n="bar_vertical_pink.png.svn-base" o="slice" g="staff" p="33060"/><f n="bar_vertical_purple.png.svn-base" o="slice" g="staff" p="33060"/><f n="bar_vertical_red.png.svn-base" o="slice" g="staff" p="33060"/><f n="bar_vertical_white.png.svn-base" o="slice" g="staff" p="33060"/><f n="graph_bg.png.svn-base" o="slice" g="staff" p="33060"/><f n="graph_bg_small.png.svn-base" o="slice" g="staff" p="33060"/></f><f n="props" o="slice" g="staff" p="16877"/><f n="text-base" o="slice" g="staff" p="16877"><f n="bar_horizontal_bg.png.svn-base" o="slice" g="staff" p="33060"/><f n="bar_horizontal_fire100.png.svn-base" o="slice" g="staff" p="33060"/><f n="bar_horizontal_fire125.png.svn-base" o="slice" g="staff" p="33060"/><f n="bar_horizontal_fire80.png.svn-base" o="slice" g="staff" p="33060"/><f n="bar_horizontal_fire82.png.svn-base" o="slice" g="staff" p="33060"/><f n="bar_horizontal_graphite.png.svn-base" o="slice" g="staff" p="33060"/><f n="bar_horizontal_orange.png.svn-base" o="slice" g="staff" p="33060"/><f n="bar_horizontal_pink.png.svn-base" o="slice" g="staff" p="33060"/><f n="bar_horizontal_purple.png.svn-base" o="slice" g="staff" p="33060"/><f n="bar_horizontal_red.png.svn-base" o="slice" g="staff" p="33060"/><f n="bar_horizontal_white.png.svn-base" o="slice" g="staff" p="33060"/><f n="bar_vertical_bg.png.svn-base" o="slice" g="staff" p="33060"/><f n="bar_vertical_graphite.png.svn-base" o="slice" g="staff" p="33060"/><f n="bar_vertical_orange.png.svn-base" o="slice" g="staff" p="33060"/><f n="bar_vertical_pink.png.svn-base" o="slice" g="staff" p="33060"/><f n="bar_vertical_purple.png.svn-base" o="slice" g="staff" p="33060"/><f n="bar_vertical_red.png.svn-base" o="slice" g="staff" p="33060"/><f n="bar_vertical_white.png.svn-base" o="slice" g="staff" p="33060"/><f n="graph_bg.png.svn-base" o="slice" g="staff" p="33060"/><f n="graph_bg_small.png.svn-base" o="slice" g="staff" p="33060"/></f><f n="tmp" o="slice" g="staff" p="16877"><f n="prop-base" o="slice" g="staff" p="16877"/><f n="props" o="slice" g="staff" p="16877"/><f n="text-base" o="slice" g="staff" p="16877"/></f></f><f n="bar_horizontal_bg.png" o="slice" g="staff" p="33216"/><f n="bar_horizontal_fire100.png" o="slice" g="staff" p="33216"/><f n="bar_horizontal_fire125.png" o="slice" g="staff" p="33216"/><f n="bar_horizontal_fire80.png" o="slice" g="staff" p="33216"/><f n="bar_horizontal_fire82.png" o="slice" g="staff" p="33216"/><f n="bar_horizontal_graphite.png" o="slice" g="staff" p="33216"/><f n="bar_horizontal_orange.png" o="slice" g="staff" p="33216"/><f n="bar_horizontal_pink.png" o="slice" g="staff" p="33216"/><f n="bar_horizontal_purple.png" o="slice" g="staff" p="33216"/><f n="bar_horizontal_red.png" o="slice" g="staff" p="33216"/><f n="bar_horizontal_white.png" o="slice" g="staff" p="33216"/><f n="bar_vertical_bg.png" o="slice" g="staff" p="33216"/><f n="bar_vertical_graphite.png" o="slice" g="staff" p="33216"/><f n="bar_vertical_orange.png" o="slice" g="staff" p="33216"/><f n="bar_vertical_pink.png" o="slice" g="staff" p="33216"/><f n="bar_vertical_purple.png" o="slice" g="staff" p="33216"/><f n="bar_vertical_red.png" o="slice" g="staff" p="33216"/><f n="bar_vertical_white.png" o="slice" g="staff" p="33216"/><f n="graph_bg.png" o="slice" g="staff" p="33216"/><f n="graph_bg_small.png" o="slice" g="staff" p="33216"/></f><f n="defaultHD.png" o="slice" g="staff" p="33216"/><f n="defaultProcessIcon.tiff" o="slice" g="staff" p="33216"/><f n="IP_copied.png" o="slice" g="staff" p="33216"/><f n="net_icon_airport.png" o="slice" g="staff" p="33216"/><f n="net_icon_airport0.png" o="slice" g="staff" p="33216"/><f n="net_icon_airport1.png" o="slice" g="staff" p="33216"/><f n="net_icon_airport2.png" o="slice" g="staff" p="33216"/><f n="net_icon_airport3.png" o="slice" g="staff" p="33216"/><f n="net_icon_airport4.png" o="slice" g="staff" p="33216"/><f n="net_icon_bluetooth.png" o="slice" g="staff" p="33216"/><f n="net_icon_ethernet.png" o="slice" g="staff" p="33216"/><f n="net_icon_firewire.png" o="slice" g="staff" p="33216"/><f n="net_icon_modem.png" o="slice" g="staff" p="33216"/><f n="net_icon_vpn.pdf" o="slice" g="staff" p="33216"/><f n="scrollbar" o="slice" g="staff" p="16832"><f n=".svn" o="slice" g="staff" p="16877"><f n="entries" o="slice" g="staff" p="33060"/><f n="prop-base" o="slice" g="staff" p="16877"><f n="barbottom.png.svn-base" o="slice" g="staff" p="33060"/><f n="barbottom_down.png.svn-base" o="slice" g="staff" p="33060"/><f n="barmid.png.svn-base" o="slice" g="staff" p="33060"/><f n="barmid_down.png.svn-base" o="slice" g="staff" p="33060"/><f n="bartop.png.svn-base" o="slice" g="staff" p="33060"/><f n="bartop_down.png.svn-base" o="slice" g="staff" p="33060"/><f n="trackbottom.png.svn-base" o="slice" g="staff" p="33060"/><f n="trackmid.png.svn-base" o="slice" g="staff" p="33060"/><f n="tracktop.png.svn-base" o="slice" g="staff" p="33060"/></f><f n="props" o="slice" g="staff" p="16877"/><f n="text-base" o="slice" g="staff" p="16877"><f n="barbottom.png.svn-base" o="slice" g="staff" p="33060"/><f n="barbottom_down.png.svn-base" o="slice" g="staff" p="33060"/><f n="barmid.png.svn-base" o="slice" g="staff" p="33060"/><f n="barmid_down.png.svn-base" o="slice" g="staff" p="33060"/><f n="bartop.png.svn-base" o="slice" g="staff" p="33060"/><f n="bartop_down.png.svn-base" o="slice" g="staff" p="33060"/><f n="trackbottom.png.svn-base" o="slice" g="staff" p="33060"/><f n="trackmid.png.svn-base" o="slice" g="staff" p="33060"/><f n="tracktop.png.svn-base" o="slice" g="staff" p="33060"/></f><f n="tmp" o="slice" g="staff" p="16877"><f n="prop-base" o="slice" g="staff" p="16877"/><f n="props" o="slice" g="staff" p="16877"/><f n="text-base" o="slice" g="staff" p="16877"/></f></f><f n="barbottom.png" o="slice" g="staff" p="33216"/><f n="barbottom_down.png" o="slice" g="staff" p="33216"/><f n="barmid.png" o="slice" g="staff" p="33216"/><f n="barmid_down.png" o="slice" g="staff" p="33216"/><f n="bartop.png" o="slice" g="staff" p="33216"/><f n="bartop_down.png" o="slice" g="staff" p="33216"/><f n="trackbottom.png" o="slice" g="staff" p="33216"/><f n="trackmid.png" o="slice" g="staff" p="33216"/><f n="tracktop.png" o="slice" g="staff" p="33216"/></f><f n="skin_tall" o="slice" g="staff" p="16832"><f n=".DS_Store" o="slice" g="staff" p="33216"/><f n=".svn" o="slice" g="staff" p="16877"><f n="entries" o="slice" g="staff" p="33060"/><f n="prop-base" o="slice" g="staff" p="16877"><f n="drag-shadow-bottom.png.svn-base" o="slice" g="staff" p="33060"/><f n="drag-shadow-top.png.svn-base" o="slice" g="staff" p="33060"/><f n="tall_activitymon.png.svn-base" o="slice" g="staff" p="33060"/><f n="tall_activitymon_rollie.png.svn-base" o="slice" g="staff" p="33060"/><f n="tall_divider.png.svn-base" o="slice" g="staff" p="33060"/><f n="tall_draghandle.png.svn-base" o="slice" g="staff" p="33060"/><f n="tall_dragsection.png.svn-base" o="slice" g="staff" p="33060"/><f n="tall_footer.png.svn-base" o="slice" g="staff" p="33060"/><f n="tall_help.png.svn-base" o="slice" g="staff" p="33060"/><f n="tall_help_rollie.png.svn-base" o="slice" g="staff" p="33060"/><f n="tall_iphone.png.svn-base" o="slice" g="staff" p="33060"/><f n="tall_iphone_rollie.png.svn-base" o="slice" g="staff" p="33060"/><f n="tall_mid.png.svn-base" o="slice" g="staff" p="33060"/><f n="tall_mid_background.png.svn-base" o="slice" g="staff" p="33060"/><f n="tall_mid_section.png.svn-base" o="slice" g="staff" p="33060"/><f n="tall_prefs.png.svn-base" o="slice" g="staff" p="33060"/><f n="tall_prefs_rollie.png.svn-base" o="slice" g="staff" p="33060"/></f><f n="props" o="slice" g="staff" p="16877"/><f n="text-base" o="slice" g="staff" p="16877"><f n="drag-shadow-bottom.png.svn-base" o="slice" g="staff" p="33060"/><f n="drag-shadow-top.png.svn-base" o="slice" g="staff" p="33060"/><f n="tall_activitymon.png.svn-base" o="slice" g="staff" p="33060"/><f n="tall_activitymon_rollie.png.svn-base" o="slice" g="staff" p="33060"/><f n="tall_divider.png.svn-base" o="slice" g="staff" p="33060"/><f n="tall_draghandle.png.svn-base" o="slice" g="staff" p="33060"/><f n="tall_dragsection.png.svn-base" o="slice" g="staff" p="33060"/><f n="tall_footer.png.svn-base" o="slice" g="staff" p="33060"/><f n="tall_help.png.svn-base" o="slice" g="staff" p="33060"/><f n="tall_help_rollie.png.svn-base" o="slice" g="staff" p="33060"/><f n="tall_iphone.png.svn-base" o="slice" g="staff" p="33060"/><f n="tall_iphone_rollie.png.svn-base" o="slice" g="staff" p="33060"/><f n="tall_mid.png.svn-base" o="slice" g="staff" p="33060"/><f n="tall_mid_background.png.svn-base" o="slice" g="staff" p="33060"/><f n="tall_mid_section.png.svn-base" o="slice" g="staff" p="33060"/><f n="tall_prefs.png.svn-base" o="slice" g="staff" p="33060"/><f n="tall_prefs_rollie.png.svn-base" o="slice" g="staff" p="33060"/></f><f n="tmp" o="slice" g="staff" p="16877"><f n="prop-base" o="slice" g="staff" p="16877"/><f n="props" o="slice" g="staff" p="16877"/><f n="text-base" o="slice" g="staff" p="16877"/></f></f><f n="drag-shadow-bottom.png" o="slice" g="staff" p="33216"/><f n="drag-shadow-top.png" o="slice" g="staff" p="33216"/><f n="skin_blue" o="slice" g="staff" p="16832"><f n=".DS_Store" o="slice" g="staff" p="33216"/><f n=".svn" o="slice" g="staff" p="16877"><f n="entries" o="slice" g="staff" p="33060"/><f n="prop-base" o="slice" g="staff" p="16877"><f n="tall_dragnewposition.png.svn-base" o="slice" g="staff" p="33060"/><f n="tall_header.png.svn-base" o="slice" g="staff" p="33060"/></f><f n="props" o="slice" g="staff" p="16877"/><f n="text-base" o="slice" g="staff" p="16877"><f n="tall_dragnewposition.png.svn-base" o="slice" g="staff" p="33060"/><f n="tall_header.png.svn-base" o="slice" g="staff" p="33060"/></f><f n="tmp" o="slice" g="staff" p="16877"><f n="prop-base" o="slice" g="staff" p="16877"/><f n="props" o="slice" g="staff" p="16877"/><f n="text-base" o="slice" g="staff" p="16877"/></f></f><f n="tall_dragnewposition.png" o="slice" g="staff" p="33216"/><f n="tall_header.png" o="slice" g="staff" p="33216"/></f><f n="skin_fire" o="slice" g="staff" p="16832"><f n=".svn" o="slice" g="staff" p="16877"><f n="entries" o="slice" g="staff" p="33060"/><f n="prop-base" o="slice" g="staff" p="16877"><f n="tall_dragnewposition.png.svn-base" o="slice" g="staff" p="33060"/><f n="tall_header.png.svn-base" o="slice" g="staff" p="33060"/></f><f n="props" o="slice" g="staff" p="16877"/><f n="text-base" o="slice" g="staff" p="16877"><f n="tall_dragnewposition.png.svn-base" o="slice" g="staff" p="33060"/><f n="tall_header.png.svn-base" o="slice" g="staff" p="33060"/></f><f n="tmp" o="slice" g="staff" p="16877"><f n="prop-base" o="slice" g="staff" p="16877"/><f n="props" o="slice" g="staff" p="16877"/><f n="text-base" o="slice" g="staff" p="16877"/></f></f><f n="tall_dragnewposition.png" o="slice" g="staff" p="33216"/><f n="tall_header.png" o="slice" g="staff" p="33216"/></f><f n="skin_graphite" o="slice" g="staff" p="16832"><f n=".DS_Store" o="slice" g="staff" p="33216"/><f n=".svn" o="slice" g="staff" p="16877"><f n="entries" o="slice" g="staff" p="33060"/><f n="prop-base" o="slice" g="staff" p="16877"><f n="tall_dragnewposition.png.svn-base" o="slice" g="staff" p="33060"/><f n="tall_header.png.svn-base" o="slice" g="staff" p="33060"/></f><f n="props" o="slice" g="staff" p="16877"/><f n="text-base" o="slice" g="staff" p="16877"><f n="tall_dragnewposition.png.svn-base" o="slice" g="staff" p="33060"/><f n="tall_header.png.svn-base" o="slice" g="staff" p="33060"/></f><f n="tmp" o="slice" g="staff" p="16877"><f n="prop-base" o="slice" g="staff" p="16877"/><f n="props" o="slice" g="staff" p="16877"/><f n="text-base" o="slice" g="staff" p="16877"/></f></f><f n="tall_dragnewposition.png" o="slice" g="staff" p="33216"/><f n="tall_header.png" o="slice" g="staff" p="33216"/></f><f n="skin_green" o="slice" g="staff" p="16832"><f n=".DS_Store" o="slice" g="staff" p="33216"/><f n=".svn" o="slice" g="staff" p="16877"><f n="entries" o="slice" g="staff" p="33060"/><f n="prop-base" o="slice" g="staff" p="16877"><f n="tall_dragnewposition.png.svn-base" o="slice" g="staff" p="33060"/><f n="tall_header.png.svn-base" o="slice" g="staff" p="33060"/></f><f n="props" o="slice" g="staff" p="16877"/><f n="text-base" o="slice" g="staff" p="16877"><f n="tall_dragnewposition.png.svn-base" o="slice" g="staff" p="33060"/><f n="tall_header.png.svn-base" o="slice" g="staff" p="33060"/></f><f n="tmp" o="slice" g="staff" p="16877"><f n="prop-base" o="slice" g="staff" p="16877"/><f n="props" o="slice" g="staff" p="16877"/><f n="text-base" o="slice" g="staff" p="16877"/></f></f><f n="tall_dragnewposition.png" o="slice" g="staff" p="33216"/><f n="tall_header.png" o="slice" g="staff" p="33216"/></f><f n="skin_grey" o="slice" g="staff" p="16832"><f n=".DS_Store" o="slice" g="staff" p="33216"/><f n=".svn" o="slice" g="staff" p="16877"><f n="entries" o="slice" g="staff" p="33060"/><f n="prop-base" o="slice" g="staff" p="16877"><f n="tall_dragnewposition.png.svn-base" o="slice" g="staff" p="33060"/><f n="tall_header.png.svn-base" o="slice" g="staff" p="33060"/></f><f n="props" o="slice" g="staff" p="16877"/><f n="text-base" o="slice" g="staff" p="16877"><f n="tall_dragnewposition.png.svn-base" o="slice" g="staff" p="33060"/><f n="tall_header.png.svn-base" o="slice" g="staff" p="33060"/></f><f n="tmp" o="slice" g="staff" p="16877"><f n="prop-base" o="slice" g="staff" p="16877"/><f n="props" o="slice" g="staff" p="16877"/><f n="text-base" o="slice" g="staff" p="16877"/></f></f><f n="tall_dragnewposition.png" o="slice" g="staff" p="33216"/><f n="tall_header.png" o="slice" g="staff" p="33216"/></f><f n="skin_pink" o="slice" g="staff" p="16832"><f n=".DS_Store" o="slice" g="staff" p="33216"/><f n=".svn" o="slice" g="staff" p="16877"><f n="entries" o="slice" g="staff" p="33060"/><f n="prop-base" o="slice" g="staff" p="16877"><f n="tall_dragnewposition.png.svn-base" o="slice" g="staff" p="33060"/><f n="tall_header.png.svn-base" o="slice" g="staff" p="33060"/></f><f n="props" o="slice" g="staff" p="16877"/><f n="text-base" o="slice" g="staff" p="16877"><f n="tall_dragnewposition.png.svn-base" o="slice" g="staff" p="33060"/><f n="tall_header.png.svn-base" o="slice" g="staff" p="33060"/></f><f n="tmp" o="slice" g="staff" p="16877"><f n="prop-base" o="slice" g="staff" p="16877"/><f n="props" o="slice" g="staff" p="16877"/><f n="text-base" o="slice" g="staff" p="16877"/></f></f><f n="tall_dragnewposition.png" o="slice" g="staff" p="33216"/><f n="tall_header.png" o="slice" g="staff" p="33216"/></f><f n="skin_purple" o="slice" g="staff" p="16832"><f n=".svn" o="slice" g="staff" p="16877"><f n="entries" o="slice" g="staff" p="33060"/><f n="prop-base" o="slice" g="staff" p="16877"><f n="tall_dragnewposition.png.svn-base" o="slice" g="staff" p="33060"/><f n="tall_header.png.svn-base" o="slice" g="staff" p="33060"/></f><f n="props" o="slice" g="staff" p="16877"/><f n="text-base" o="slice" g="staff" p="16877"><f n="tall_dragnewposition.png.svn-base" o="slice" g="staff" p="33060"/><f n="tall_header.png.svn-base" o="slice" g="staff" p="33060"/></f><f n="tmp" o="slice" g="staff" p="16877"><f n="prop-base" o="slice" g="staff" p="16877"/><f n="props" o="slice" g="staff" p="16877"/><f n="text-base" o="slice" g="staff" p="16877"/></f></f><f n="tall_dragnewposition.png" o="slice" g="staff" p="33216"/><f n="tall_header.png" o="slice" g="staff" p="33216"/></f><f n="skin_putty" o="slice" g="staff" p="16832"><f n=".DS_Store" o="slice" g="staff" p="33216"/><f n=".svn" o="slice" g="staff" p="16877"><f n="entries" o="slice" g="staff" p="33060"/><f n="prop-base" o="slice" g="staff" p="16877"><f n="tall_dragnewposition.png.svn-base" o="slice" g="staff" p="33060"/><f n="tall_header.png.svn-base" o="slice" g="staff" p="33060"/></f><f n="props" o="slice" g="staff" p="16877"/><f n="text-base" o="slice" g="staff" p="16877"><f n="tall_dragnewposition.png.svn-base" o="slice" g="staff" p="33060"/><f n="tall_header.png.svn-base" o="slice" g="staff" p="33060"/></f><f n="tmp" o="slice" g="staff" p="16877"><f n="prop-base" o="slice" g="staff" p="16877"/><f n="props" o="slice" g="staff" p="16877"/><f n="text-base" o="slice" g="staff" p="16877"/></f></f><f n="tall_dragnewposition.png" o="slice" g="staff" p="33216"/><f n="tall_header.png" o="slice" g="staff" p="33216"/></f><f n="skin_red" o="slice" g="staff" p="16832"><f n=".DS_Store" o="slice" g="staff" p="33216"/><f n=".svn" o="slice" g="staff" p="16877"><f n="entries" o="slice" g="staff" p="33060"/><f n="prop-base" o="slice" g="staff" p="16877"><f n="tall_dragnewposition.png.svn-base" o="slice" g="staff" p="33060"/><f n="tall_header.png.svn-base" o="slice" g="staff" p="33060"/></f><f n="props" o="slice" g="staff" p="16877"/><f n="text-base" o="slice" g="staff" p="16877"><f n="tall_dragnewposition.png.svn-base" o="slice" g="staff" p="33060"/><f n="tall_header.png.svn-base" o="slice" g="staff" p="33060"/></f><f n="tmp" o="slice" g="staff" p="16877"><f n="prop-base" o="slice" g="staff" p="16877"/><f n="props" o="slice" g="staff" p="16877"/><f n="text-base" o="slice" g="staff" p="16877"/></f></f><f n="tall_dragnewposition.png" o="slice" g="staff" p="33216"/><f n="tall_header.png" o="slice" g="staff" p="33216"/></f><f n="tall_activitymon.png" o="slice" g="staff" p="33216"/><f n="tall_activitymon_rollie.png" o="slice" g="staff" p="33216"/><f n="tall_divider.png" o="slice" g="staff" p="33216"/><f n="tall_draghandle.png" o="slice" g="staff" p="33216"/><f n="tall_dragsection.png" o="slice" g="staff" p="33216"/><f n="tall_footer.png" o="slice" g="staff" p="33216"/><f n="tall_help.png" o="slice" g="staff" p="33216"/><f n="tall_help_rollie.png" o="slice" g="staff" p="33216"/><f n="tall_iphone.png" o="slice" g="staff" p="33216"/><f n="tall_iphone_rollie.png" o="slice" g="staff" p="33216"/><f n="tall_mid.png" o="slice" g="staff" p="33216"/><f n="tall_mid_background.png" o="slice" g="staff" p="33216"/><f n="tall_mid_section.png" o="slice" g="staff" p="33216"/><f n="tall_prefs.png" o="slice" g="staff" p="33216"/><f n="tall_prefs_rollie.png" o="slice" g="staff" p="33216"/></f><f n="skin_wide" o="slice" g="staff" p="16832"><f n=".DS_Store" o="slice" g="staff" p="33216"/><f n=".svn" o="slice" g="staff" p="16877"><f n="entries" o="slice" g="staff" p="33060"/><f n="prop-base" o="slice" g="staff" p="16877"><f n="drag-shadow-left.png.svn-base" o="slice" g="staff" p="33060"/><f n="drag-shadow-right.png.svn-base" o="slice" g="staff" p="33060"/><f n="wide_activitymon.png.svn-base" o="slice" g="staff" p="33060"/><f n="wide_activitymon_rollie.png.svn-base" o="slice" g="staff" p="33060"/><f n="wide_divider.png.svn-base" o="slice" g="staff" p="33060"/><f n="wide_draghandle.png.svn-base" o="slice" g="staff" p="33060"/><f n="wide_dragsection.png.svn-base" o="slice" g="staff" p="33060"/><f n="wide_footer.png.svn-base" o="slice" g="staff" p="33060"/><f n="wide_help.png.svn-base" o="slice" g="staff" p="33060"/><f n="wide_help_rollie.png.svn-base" o="slice" g="staff" p="33060"/><f n="wide_iphone.png.svn-base" o="slice" g="staff" p="33060"/><f n="wide_iphone_rollie.png.svn-base" o="slice" g="staff" p="33060"/><f n="wide_mid.png.svn-base" o="slice" g="staff" p="33060"/><f n="wide_mid_background.png.svn-base" o="slice" g="staff" p="33060"/><f n="wide_mid_section.png.svn-base" o="slice" g="staff" p="33060"/><f n="wide_prefs.png.svn-base" o="slice" g="staff" p="33060"/><f n="wide_prefs_rollie.png.svn-base" o="slice" g="staff" p="33060"/></f><f n="props" o="slice" g="staff" p="16877"/><f n="text-base" o="slice" g="staff" p="16877"><f n="drag-shadow-left.png.svn-base" o="slice" g="staff" p="33060"/><f n="drag-shadow-right.png.svn-base" o="slice" g="staff" p="33060"/><f n="wide_activitymon.png.svn-base" o="slice" g="staff" p="33060"/><f n="wide_activitymon_rollie.png.svn-base" o="slice" g="staff" p="33060"/><f n="wide_divider.png.svn-base" o="slice" g="staff" p="33060"/><f n="wide_draghandle.png.svn-base" o="slice" g="staff" p="33060"/><f n="wide_dragsection.png.svn-base" o="slice" g="staff" p="33060"/><f n="wide_footer.png.svn-base" o="slice" g="staff" p="33060"/><f n="wide_help.png.svn-base" o="slice" g="staff" p="33060"/><f n="wide_help_rollie.png.svn-base" o="slice" g="staff" p="33060"/><f n="wide_iphone.png.svn-base" o="slice" g="staff" p="33060"/><f n="wide_iphone_rollie.png.svn-base" o="slice" g="staff" p="33060"/><f n="wide_mid.png.svn-base" o="slice" g="staff" p="33060"/><f n="wide_mid_background.png.svn-base" o="slice" g="staff" p="33060"/><f n="wide_mid_section.png.svn-base" o="slice" g="staff" p="33060"/><f n="wide_prefs.png.svn-base" o="slice" g="staff" p="33060"/><f n="wide_prefs_rollie.png.svn-base" o="slice" g="staff" p="33060"/></f><f n="tmp" o="slice" g="staff" p="16877"><f n="prop-base" o="slice" g="staff" p="16877"/><f n="props" o="slice" g="staff" p="16877"/><f n="text-base" o="slice" g="staff" p="16877"/></f></f><f n="drag-shadow-left.png" o="slice" g="staff" p="33216"/><f n="drag-shadow-right.png" o="slice" g="staff" p="33216"/><f n="skin_blue" o="slice" g="staff" p="16832"><f n=".DS_Store" o="slice" g="staff" p="33216"/><f n=".svn" o="slice" g="staff" p="16877"><f n="entries" o="slice" g="staff" p="33060"/><f n="prop-base" o="slice" g="staff" p="16877"><f n="wide_dragnewposition.png.svn-base" o="slice" g="staff" p="33060"/><f n="wide_header.png.svn-base" o="slice" g="staff" p="33060"/></f><f n="props" o="slice" g="staff" p="16877"/><f n="text-base" o="slice" g="staff" p="16877"><f n="wide_dragnewposition.png.svn-base" o="slice" g="staff" p="33060"/><f n="wide_header.png.svn-base" o="slice" g="staff" p="33060"/></f><f n="tmp" o="slice" g="staff" p="16877"><f n="prop-base" o="slice" g="staff" p="16877"/><f n="props" o="slice" g="staff" p="16877"/><f n="text-base" o="slice" g="staff" p="16877"/></f></f><f n="wide_dragnewposition.png" o="slice" g="staff" p="33216"/><f n="wide_header.png" o="slice" g="staff" p="33216"/></f><f n="skin_fire" o="slice" g="staff" p="16832"><f n=".svn" o="slice" g="staff" p="16877"><f n="entries" o="slice" g="staff" p="33060"/><f n="prop-base" o="slice" g="staff" p="16877"><f n="wide_dragnewposition.png.svn-base" o="slice" g="staff" p="33060"/><f n="wide_header.png.svn-base" o="slice" g="staff" p="33060"/></f><f n="props" o="slice" g="staff" p="16877"/><f n="text-base" o="slice" g="staff" p="16877"><f n="wide_dragnewposition.png.svn-base" o="slice" g="staff" p="33060"/><f n="wide_header.png.svn-base" o="slice" g="staff" p="33060"/></f><f n="tmp" o="slice" g="staff" p="16877"><f n="prop-base" o="slice" g="staff" p="16877"/><f n="props" o="slice" g="staff" p="16877"/><f n="text-base" o="slice" g="staff" p="16877"/></f></f><f n="wide_dragnewposition.png" o="slice" g="staff" p="33216"/><f n="wide_header.png" o="slice" g="staff" p="33216"/></f><f n="skin_graphite" o="slice" g="staff" p="16832"><f n=".svn" o="slice" g="staff" p="16877"><f n="entries" o="slice" g="staff" p="33060"/><f n="prop-base" o="slice" g="staff" p="16877"><f n="wide_dragnewposition.png.svn-base" o="slice" g="staff" p="33060"/><f n="wide_header.png.svn-base" o="slice" g="staff" p="33060"/></f><f n="props" o="slice" g="staff" p="16877"/><f n="text-base" o="slice" g="staff" p="16877"><f n="wide_dragnewposition.png.svn-base" o="slice" g="staff" p="33060"/><f n="wide_header.png.svn-base" o="slice" g="staff" p="33060"/></f><f n="tmp" o="slice" g="staff" p="16877"><f n="prop-base" o="slice" g="staff" p="16877"/><f n="props" o="slice" g="staff" p="16877"/><f n="text-base" o="slice" g="staff" p="16877"/></f></f><f n="wide_dragnewposition.png" o="slice" g="staff" p="33216"/><f n="wide_header.png" o="slice" g="staff" p="33216"/></f><f n="skin_green" o="slice" g="staff" p="16832"><f n=".svn" o="slice" g="staff" p="16877"><f n="entries" o="slice" g="staff" p="33060"/><f n="prop-base" o="slice" g="staff" p="16877"><f n="wide_dragnewposition.png.svn-base" o="slice" g="staff" p="33060"/><f n="wide_header.png.svn-base" o="slice" g="staff" p="33060"/></f><f n="props" o="slice" g="staff" p="16877"/><f n="text-base" o="slice" g="staff" p="16877"><f n="wide_dragnewposition.png.svn-base" o="slice" g="staff" p="33060"/><f n="wide_header.png.svn-base" o="slice" g="staff" p="33060"/></f><f n="tmp" o="slice" g="staff" p="16877"><f n="prop-base" o="slice" g="staff" p="16877"/><f n="props" o="slice" g="staff" p="16877"/><f n="text-base" o="slice" g="staff" p="16877"/></f></f><f n="wide_dragnewposition.png" o="slice" g="staff" p="33216"/><f n="wide_header.png" o="slice" g="staff" p="33216"/></f><f n="skin_grey" o="slice" g="staff" p="16832"><f n=".svn" o="slice" g="staff" p="16877"><f n="entries" o="slice" g="staff" p="33060"/><f n="prop-base" o="slice" g="staff" p="16877"><f n="wide_dragnewposition.png.svn-base" o="slice" g="staff" p="33060"/><f n="wide_header.png.svn-base" o="slice" g="staff" p="33060"/></f><f n="props" o="slice" g="staff" p="16877"/><f n="text-base" o="slice" g="staff" p="16877"><f n="wide_dragnewposition.png.svn-base" o="slice" g="staff" p="33060"/><f n="wide_header.png.svn-base" o="slice" g="staff" p="33060"/></f><f n="tmp" o="slice" g="staff" p="16877"><f n="prop-base" o="slice" g="staff" p="16877"/><f n="props" o="slice" g="staff" p="16877"/><f n="text-base" o="slice" g="staff" p="16877"/></f></f><f n="wide_dragnewposition.png" o="slice" g="staff" p="33216"/><f n="wide_header.png" o="slice" g="staff" p="33216"/></f><f n="skin_pink" o="slice" g="staff" p="16832"><f n=".svn" o="slice" g="staff" p="16877"><f n="entries" o="slice" g="staff" p="33060"/><f n="prop-base" o="slice" g="staff" p="16877"><f n="wide_dragnewposition.png.svn-base" o="slice" g="staff" p="33060"/><f n="wide_header.png.svn-base" o="slice" g="staff" p="33060"/></f><f n="props" o="slice" g="staff" p="16877"/><f n="text-base" o="slice" g="staff" p="16877"><f n="wide_dragnewposition.png.svn-base" o="slice" g="staff" p="33060"/><f n="wide_header.png.svn-base" o="slice" g="staff" p="33060"/></f><f n="tmp" o="slice" g="staff" p="16877"><f n="prop-base" o="slice" g="staff" p="16877"/><f n="props" o="slice" g="staff" p="16877"/><f n="text-base" o="slice" g="staff" p="16877"/></f></f><f n="wide_dragnewposition.png" o="slice" g="staff" p="33216"/><f n="wide_header.png" o="slice" g="staff" p="33216"/></f><f n="skin_purple" o="slice" g="staff" p="16832"><f n=".svn" o="slice" g="staff" p="16877"><f n="entries" o="slice" g="staff" p="33060"/><f n="prop-base" o="slice" g="staff" p="16877"><f n="wide_dragnewposition.png.svn-base" o="slice" g="staff" p="33060"/><f n="wide_header.png.svn-base" o="slice" g="staff" p="33060"/></f><f n="props" o="slice" g="staff" p="16877"/><f n="text-base" o="slice" g="staff" p="16877"><f n="wide_dragnewposition.png.svn-base" o="slice" g="staff" p="33060"/><f n="wide_header.png.svn-base" o="slice" g="staff" p="33060"/></f><f n="tmp" o="slice" g="staff" p="16877"><f n="prop-base" o="slice" g="staff" p="16877"/><f n="props" o="slice" g="staff" p="16877"/><f n="text-base" o="slice" g="staff" p="16877"/></f></f><f n="wide_dragnewposition.png" o="slice" g="staff" p="33216"/><f n="wide_header.png" o="slice" g="staff" p="33216"/></f><f n="skin_putty" o="slice" g="staff" p="16832"><f n=".svn" o="slice" g="staff" p="16877"><f n="entries" o="slice" g="staff" p="33060"/><f n="prop-base" o="slice" g="staff" p="16877"><f n="wide_dragnewposition.png.svn-base" o="slice" g="staff" p="33060"/><f n="wide_header.png.svn-base" o="slice" g="staff" p="33060"/></f><f n="props" o="slice" g="staff" p="16877"/><f n="text-base" o="slice" g="staff" p="16877"><f n="wide_dragnewposition.png.svn-base" o="slice" g="staff" p="33060"/><f n="wide_header.png.svn-base" o="slice" g="staff" p="33060"/></f><f n="tmp" o="slice" g="staff" p="16877"><f n="prop-base" o="slice" g="staff" p="16877"/><f n="props" o="slice" g="staff" p="16877"/><f n="text-base" o="slice" g="staff" p="16877"/></f></f><f n="wide_dragnewposition.png" o="slice" g="staff" p="33216"/><f n="wide_header.png" o="slice" g="staff" p="33216"/></f><f n="skin_red" o="slice" g="staff" p="16832"><f n=".svn" o="slice" g="staff" p="16877"><f n="entries" o="slice" g="staff" p="33060"/><f n="prop-base" o="slice" g="staff" p="16877"><f n="wide_dragnewposition.png.svn-base" o="slice" g="staff" p="33060"/><f n="wide_header.png.svn-base" o="slice" g="staff" p="33060"/></f><f n="props" o="slice" g="staff" p="16877"/><f n="text-base" o="slice" g="staff" p="16877"><f n="wide_dragnewposition.png.svn-base" o="slice" g="staff" p="33060"/><f n="wide_header.png.svn-base" o="slice" g="staff" p="33060"/></f><f n="tmp" o="slice" g="staff" p="16877"><f n="prop-base" o="slice" g="staff" p="16877"/><f n="props" o="slice" g="staff" p="16877"/><f n="text-base" o="slice" g="staff" p="16877"/></f></f><f n="wide_dragnewposition.png" o="slice" g="staff" p="33216"/><f n="wide_header.png" o="slice" g="staff" p="33216"/></f><f n="wide_activitymon.png" o="slice" g="staff" p="33216"/><f n="wide_activitymon_rollie.png" o="slice" g="staff" p="33216"/><f n="wide_divider.png" o="slice" g="staff" p="33216"/><f n="wide_draghandle.png" o="slice" g="staff" p="33216"/><f n="wide_dragsection.png" o="slice" g="staff" p="33216"/><f n="wide_footer.png" o="slice" g="staff" p="33216"/><f n="wide_help.png" o="slice" g="staff" p="33216"/><f n="wide_help_rollie.png" o="slice" g="staff" p="33216"/><f n="wide_iphone.png" o="slice" g="staff" p="33216"/><f n="wide_iphone_rollie.png" o="slice" g="staff" p="33216"/><f n="wide_mid.png" o="slice" g="staff" p="33216"/><f n="wide_mid_background.png" o="slice" g="staff" p="33216"/><f n="wide_mid_section.png" o="slice" g="staff" p="33216"/><f n="wide_prefs.png" o="slice" g="staff" p="33216"/><f n="wide_prefs_rollie.png" o="slice" g="staff" p="33216"/></f><f n="tooltips" o="slice" g="staff" p="16832"><f n=".svn" o="slice" g="staff" p="16877"><f n="entries" o="slice" g="staff" p="33060"/><f n="prop-base" o="slice" g="staff" p="16877"><f n="tooltip_tall_activitymon.png.svn-base" o="slice" g="staff" p="33060"/><f n="tooltip_tall_help.png.svn-base" o="slice" g="staff" p="33060"/><f n="tooltip_tall_iphone.png.svn-base" o="slice" g="staff" p="33060"/><f n="tooltip_tall_settings.png.svn-base" o="slice" g="staff" p="33060"/><f n="tooltip_wide_activitymon.png.svn-base" o="slice" g="staff" p="33060"/><f n="tooltip_wide_help.png.svn-base" o="slice" g="staff" p="33060"/><f n="tooltip_wide_istat.png.svn-base" o="slice" g="staff" p="33060"/><f n="tooltip_wide_settings.png.svn-base" o="slice" g="staff" p="33060"/></f><f n="props" o="slice" g="staff" p="16877"/><f n="text-base" o="slice" g="staff" p="16877"><f n="tooltip_tall_activitymon.png.svn-base" o="slice" g="staff" p="33060"/><f n="tooltip_tall_help.png.svn-base" o="slice" g="staff" p="33060"/><f n="tooltip_tall_iphone.png.svn-base" o="slice" g="staff" p="33060"/><f n="tooltip_tall_settings.png.svn-base" o="slice" g="staff" p="33060"/><f n="tooltip_wide_activitymon.png.svn-base" o="slice" g="staff" p="33060"/><f n="tooltip_wide_help.png.svn-base" o="slice" g="staff" p="33060"/><f n="tooltip_wide_istat.png.svn-base" o="slice" g="staff" p="33060"/><f n="tooltip_wide_settings.png.svn-base" o="slice" g="staff" p="33060"/></f><f n="tmp" o="slice" g="staff" p="16877"><f n="prop-base" o="slice" g="staff" p="16877"/><f n="props" o="slice" g="staff" p="16877"/><f n="text-base" o="slice" g="staff" p="16877"/></f></f><f n="tooltip_tall_activitymon.png" o="slice" g="staff" p="33216"/><f n="tooltip_tall_help.png" o="slice" g="staff" p="33216"/><f n="tooltip_tall_iphone.png" o="slice" g="staff" p="33216"/><f n="tooltip_tall_settings.png" o="slice" g="staff" p="33216"/><f n="tooltip_wide_activitymon.png" o="slice" g="staff" p="33216"/><f n="tooltip_wide_help.png" o="slice" g="staff" p="33216"/><f n="tooltip_wide_istat.png" o="slice" g="staff" p="33216"/><f n="tooltip_wide_settings.png" o="slice" g="staff" p="33216"/></f><f n="windows" o="slice" g="staff" p="16832"><f n=".DS_Store" o="slice" g="staff" p="33216"/><f n=".svn" o="slice" g="staff" p="16877"><f n="entries" o="slice" g="staff" p="33060"/><f n="prop-base" o="slice" g="staff" p="16877"><f n="button_info.png.svn-base" o="slice" g="staff" p="33060"/><f n="button_info_rolie.png.svn-base" o="slice" g="staff" p="33060"/><f n="button_no.png.svn-base" o="slice" g="staff" p="33060"/><f n="button_no_rollie.png.svn-base" o="slice" g="staff" p="33060"/><f n="button_ok.png.svn-base" o="slice" g="staff" p="33060"/><f n="button_ok_rollie.png.svn-base" o="slice" g="staff" p="33060"/><f n="button_yes.png.svn-base" o="slice" g="staff" p="33060"/><f n="button_yes_rollie.png.svn-base" o="slice" g="staff" p="33060"/><f n="window_tall_install.png.svn-base" o="slice" g="staff" p="33060"/><f n="window_tall_iphone.png.svn-base" o="slice" g="staff" p="33060"/><f n="window_tall_noupdate.png.svn-base" o="slice" g="staff" p="33060"/><f n="window_tall_update.png.svn-base" o="slice" g="staff" p="33060"/><f n="window_wide_install.png.svn-base" o="slice" g="staff" p="33060"/><f n="window_wide_iphone.png.svn-base" o="slice" g="staff" p="33060"/><f n="window_wide_noupdate.png.svn-base" o="slice" g="staff" p="33060"/><f n="window_wide_update.png.svn-base" o="slice" g="staff" p="33060"/></f><f n="props" o="slice" g="staff" p="16877"/><f n="text-base" o="slice" g="staff" p="16877"><f n="button_info.png.svn-base" o="slice" g="staff" p="33060"/><f n="button_info_rolie.png.svn-base" o="slice" g="staff" p="33060"/><f n="button_no.png.svn-base" o="slice" g="staff" p="33060"/><f n="button_no_rollie.png.svn-base" o="slice" g="staff" p="33060"/><f n="button_ok.png.svn-base" o="slice" g="staff" p="33060"/><f n="button_ok_rollie.png.svn-base" o="slice" g="staff" p="33060"/><f n="button_yes.png.svn-base" o="slice" g="staff" p="33060"/><f n="button_yes_rollie.png.svn-base" o="slice" g="staff" p="33060"/><f n="window_tall_install.png.svn-base" o="slice" g="staff" p="33060"/><f n="window_tall_iphone.png.svn-base" o="slice" g="staff" p="33060"/><f n="window_tall_noupdate.png.svn-base" o="slice" g="staff" p="33060"/><f n="window_tall_update.png.svn-base" o="slice" g="staff" p="33060"/><f n="window_wide_install.png.svn-base" o="slice" g="staff" p="33060"/><f n="window_wide_iphone.png.svn-base" o="slice" g="staff" p="33060"/><f n="window_wide_noupdate.png.svn-base" o="slice" g="staff" p="33060"/><f n="window_wide_update.png.svn-base" o="slice" g="staff" p="33060"/></f><f n="tmp" o="slice" g="staff" p="16877"><f n="prop-base" o="slice" g="staff" p="16877"/><f n="props" o="slice" g="staff" p="16877"/><f n="text-base" o="slice" g="staff" p="16877"/></f></f><f n="button_info.png" o="slice" g="staff" p="33216"/><f n="button_info_rolie.png" o="slice" g="staff" p="33216"/><f n="button_no.png" o="slice" g="staff" p="33216"/><f n="button_no_rollie.png" o="slice" g="staff" p="33216"/><f n="button_ok.png" o="slice" g="staff" p="33216"/><f n="button_ok_rollie.png" o="slice" g="staff" p="33216"/><f n="button_yes.png" o="slice" g="staff" p="33216"/><f n="button_yes_rollie.png" o="slice" g="staff" p="33216"/><f n="window_tall_install.png" o="slice" g="staff" p="33216"/><f n="window_tall_iphone.png" o="slice" g="staff" p="33216"/><f n="window_tall_noupdate.png" o="slice" g="staff" p="33216"/><f n="window_tall_update.png" o="slice" g="staff" p="33216"/><f n="window_wide_install.png" o="slice" g="staff" p="33216"/><f n="window_wide_iphone.png" o="slice" g="staff" p="33216"/><f n="window_wide_noupdate.png" o="slice" g="staff" p="33216"/><f n="window_wide_update.png" o="slice" g="staff" p="33216"/></f></f><f n="Info.plist" o="slice" g="staff" p="33216"/><f n="iStatPro.bundle" o="slice" g="staff" p="16877"><f n=".svn" o="slice" g="staff" p="16877"><f n="entries" o="slice" g="staff" p="33060"/><f n="prop-base" o="slice" g="staff" p="16877"/><f n="props" o="slice" g="staff" p="16877"/><f n="text-base" o="slice" g="staff" p="16877"/><f n="tmp" o="slice" g="staff" p="16877"><f n="prop-base" o="slice" g="staff" p="16877"/><f n="props" o="slice" g="staff" p="16877"/><f n="text-base" o="slice" g="staff" p="16877"/></f></f><f n="Contents" o="slice" g="staff" p="16877"><f n=".svn" o="slice" g="staff" p="16877"><f n="entries" o="slice" g="staff" p="33060"/><f n="prop-base" o="slice" g="staff" p="16877"/><f n="props" o="slice" g="staff" p="16877"/><f n="text-base" o="slice" g="staff" p="16877"><f n="Info.plist.svn-base" o="slice" g="staff" p="33060"/></f><f n="tmp" o="slice" g="staff" p="16877"><f n="prop-base" o="slice" g="staff" p="16877"/><f n="props" o="slice" g="staff" p="16877"/><f n="text-base" o="slice" g="staff" p="16877"/></f></f><f n="Info.plist" o="slice" g="staff" p="33188"/><f n="MacOS" o="slice" g="staff" p="16877"><f n=".svn" o="slice" g="staff" p="16877"><f n="entries" o="slice" g="staff" p="33060"/><f n="prop-base" o="slice" g="staff" p="16877"><f n="iStatPro.svn-base" o="slice" g="staff" p="33060"/></f><f n="props" o="slice" g="staff" p="16877"/><f n="text-base" o="slice" g="staff" p="16877"><f n="iStatPro.svn-base" o="slice" g="staff" p="33060"/></f><f n="tmp" o="slice" g="staff" p="16877"><f n="prop-base" o="slice" g="staff" p="16877"/><f n="props" o="slice" g="staff" p="16877"/><f n="text-base" o="slice" g="staff" p="16877"/></f></f><f n="iStatPro" o="slice" g="staff" p="33261"/></f><f n="Resources" o="slice" g="staff" p="16877"><f n=".svn" o="slice" g="staff" p="16877"><f n="entries" o="slice" g="staff" p="33060"/><f n="prop-base" o="slice" g="staff" p="16877"><f n="LICENSE.svn-base" o="slice" g="staff" p="33060"/></f><f n="props" o="slice" g="staff" p="16877"/><f n="text-base" o="slice" g="staff" p="16877"><f n="LICENSE.svn-base" o="slice" g="staff" p="33060"/></f><f n="tmp" o="slice" g="staff" p="16877"><f n="prop-base" o="slice" g="staff" p="16877"/><f n="props" o="slice" g="staff" p="16877"/><f n="text-base" o="slice" g="staff" p="16877"/></f></f><f n="English.lproj" o="slice" g="staff" p="16877"><f n=".svn" o="slice" g="staff" p="16877"><f n="entries" o="slice" g="staff" p="33060"/><f n="prop-base" o="slice" g="staff" p="16877"><f n="InfoPlist.strings.svn-base" o="slice" g="staff" p="33060"/></f><f n="props" o="slice" g="staff" p="16877"/><f n="text-base" o="slice" g="staff" p="16877"><f n="InfoPlist.strings.svn-base" o="slice" g="staff" p="33060"/></f><f n="tmp" o="slice" g="staff" p="16877"><f n="prop-base" o="slice" g="staff" p="16877"/><f n="props" o="slice" g="staff" p="16877"/><f n="text-base" o="slice" g="staff" p="16877"/></f></f><f n="InfoPlist.strings" o="slice" g="staff" p="33188"/></f><f n="LICENSE" o="slice" g="staff" p="33261"/></f></f></f><f n="iStatpro.html" o="slice" g="staff" p="33216"/><f n="NetworkObject.js" o="slice" g="staff" p="33216"/><f n="scripts" o="slice" g="staff" p="16832"><f n=".svn" o="slice" g="staff" p="16877"><f n="entries" o="slice" g="staff" p="33060"/><f n="prop-base" o="slice" g="staff" p="16877"><f n="core.js.svn-base" o="slice" g="staff" p="33060"/><f n="dash.js.svn-base" o="slice" g="staff" p="33060"/><f n="display_prefs.js.svn-base" o="slice" g="staff" p="33060"/><f n="dragTall.js.svn-base" o="slice" g="staff" p="33060"/><f n="dragWide.js.svn-base" o="slice" g="staff" p="33060"/><f n="prefs.js.svn-base" o="slice" g="staff" p="33060"/><f n="updater.js.svn-base" o="slice" g="staff" p="33060"/></f><f n="props" o="slice" g="staff" p="16877"/><f n="text-base" o="slice" g="staff" p="16877"><f n="core.js.svn-base" o="slice" g="staff" p="33060"/><f n="dash.js.svn-base" o="slice" g="staff" p="33060"/><f n="display_prefs.js.svn-base" o="slice" g="staff" p="33060"/><f n="dragTall.js.svn-base" o="slice" g="staff" p="33060"/><f n="dragWide.js.svn-base" o="slice" g="staff" p="33060"/><f n="prefs.js.svn-base" o="slice" g="staff" p="33060"/><f n="updater.js.svn-base" o="slice" g="staff" p="33060"/></f><f n="tmp" o="slice" g="staff" p="16877"><f n="prop-base" o="slice" g="staff" p="16877"/><f n="props" o="slice" g="staff" p="16877"/><f n="text-base" o="slice" g="staff" p="16877"/></f></f><f n="core.js" o="slice" g="staff" p="33216"/><f n="dash.js" o="slice" g="staff" p="33216"/><f n="display_prefs.js" o="slice" g="staff" p="33216"/><f n="dragTall.js" o="slice" g="staff" p="33216"/><f n="dragWide.js" o="slice" g="staff" p="33216"/><f n="prefs.js" o="slice" g="staff" p="33216"/><f n="updater.js" o="slice" g="staff" p="33216"/></f><f n="Tall.js" o="slice" g="staff" p="33216"/><f n="Wide.js" o="slice" g="staff" p="33216"/><f n="Workers.js" o="slice" g="staff" p="33216"/></f></pkg-contents>